{"loaded_from_firestore": false, "total_pageviews": 1, "total_script_runs": 30, "total_time_seconds": 77577.98017099999, "per_day": {"days": ["2021-04-30", "2021-05-01", "2021-05-02"], "pageviews": [0, 1, 0], "script_runs": [0, 19, 11]}, "widgets": {"Choose a page": {"Homepage": 1, "Team Analysis": 1, "Player Analysis": 0}, "Choose a team to scout": {"Amherst": 1, "Bates": 0, "Colby": 0, "Hamilton": 0, "Middlebury": 0, "Trinity": 0}, "Choose opponents to include in the scouting report": {"Wisconsin": 1, "Middlebury": 2, "Wesleyan": 1, "Baruch": 1, "Williams": 0}, "Run!": 22}, "start_time": "01 May 2021, 17:46:31"}